CHANGES.txt
LICENSE.txt
README.txt
decken
ez_setup.py
plugin.txt
setup.py
yugioh.txt
Decken.egg-info/PKG-INFO
Decken.egg-info/SOURCES.txt
Decken.egg-info/dependency_links.txt
Decken.egg-info/requires.txt
Decken.egg-info/top_level.txt
bin/decken_n800
bin/decken_script
decken/__init__.py
decken/ui.py
decken/uigtk.py
decken/uin800.py