Metadata-Version: 1.0
Name: Decken
Version: 0.2.2
Summary: Deck Organizer to Trading Card Games
Home-page: UNKNOWN
Author: Claudio Torcato
Author-email: claudiotorcato@gmail.com
License: LICENSE.txt
Keywords: tcg mtg magic deck card python gnome linux mac n800
Platform: UNKNOWN
